muuusiiik/__init__.py
muuusiiik/util.py
muuusiiik-0.0.12.dist-info/LICENSE
muuusiiik-0.0.12.dist-info/METADATA
muuusiiik-0.0.12.dist-info/WHEEL
muuusiiik-0.0.12.dist-info/top_level.txt
muuusiiik-0.0.12.dist-info/RECORD
