Metadata-Version: 2.1
Name: muuusiiik
Version: 0.0.12
Summary: simple utilities
Home-page: https://github.com/muuusiiik/utility
Author: @muuusiiik
Author-email: muuusiiikd@gmail.com
License: MIT
Platform: UNKNOWN
Classifier: License :: OSI Approved :: MIT License
Classifier: Programming Language :: Python :: 3
Classifier: Programming Language :: Python :: 3.7
Requires-Python: >=3.7
License-File: LICENSE
Requires-Dist: dill
Requires-Dist: PyYaml
